PLCP/PLCP.py
PLCP/__init__.py
PLCP-0.1.dist-info/METADATA
PLCP-0.1.dist-info/WHEEL
PLCP-0.1.dist-info/license.txt
PLCP-0.1.dist-info/top_level.txt
PLCP-0.1.dist-info/RECORD
