Metadata-Version: 2.1
Name: PLCP
Version: 0.1
Summary: A simple encryption and decryption library
Home-page: https://upload.pypi.org/legacy/
Author: PLC_PEIRIS
Author-email: lashen985832@gmail.com
Classifier: Programming Language :: Python :: 3
Classifier: Operating System :: OS Independent
License-File: license.txt
